plott_core/__init__.py
plott_core/client.py
plott_core/events.py
plott_core/py.typed
plott_core/types.py
plott_sdk_core-0.0.1a1.dist-info/METADATA
plott_sdk_core-0.0.1a1.dist-info/WHEEL
plott_sdk_core-0.0.1a1.dist-info/RECORD
