Metadata-Version: 2.4
Name: plott-sdk-core
Version: 0.0.1a1
Summary: Plott Analytics SDK Core for Python - Event tracking and batching
Project-URL: Homepage, https://plott.ai
Project-URL: Documentation, https://docs.plott.ai/sdk
Author-email: Plott Analytics <hello@plott.ai>
License-Expression: Apache-2.0
Keywords: ai,analytics,events,llm,plott,tracking
Classifier: Development Status :: 4 - Beta
Classifier: Intended Audience :: Developers
Classifier: License :: OSI Approved :: MIT License
Classifier: Programming Language :: Python :: 3
Classifier: Programming Language :: Python :: 3.9
Classifier: Programming Language :: Python :: 3.10
Classifier: Programming Language :: Python :: 3.11
Classifier: Programming Language :: Python :: 3.12
Classifier: Topic :: Software Development :: Libraries :: Python Modules
Classifier: Typing :: Typed
Requires-Python: >=3.9
Requires-Dist: httpx>=0.24.0
Requires-Dist: typing-extensions>=4.0.0
Provides-Extra: dev
Requires-Dist: mypy>=1.0.0; extra == 'dev'
Requires-Dist: pytest-asyncio>=0.21.0; extra == 'dev'
Requires-Dist: pytest-cov>=4.0.0; extra == 'dev'
Requires-Dist: pytest>=7.0.0; extra == 'dev'
Requires-Dist: ruff>=0.1.0; extra == 'dev'
